{
  "brand": "teneo",
  "name": "Teneo Revolutionary Library",
  "description": "AI-generated books revealing hidden truths and paradigm-shifting insights",
  "books": [
    {
      "id": "consciousness-revolution",
      "title": "The Consciousness Revolution",
      "author": "Dr. Marcus Reid & Teneo AI",
      "description": "How AI is revealing the true nature of human awareness",
      "longDescription": "REVOLUTIONARY DISCOVERY! This groundbreaking work reveals how artificial intelligence is uncovering the hidden mechanics of consciousness itself.",
      "price": 29.99,
      "originalPrice": 49.99,
      "hardcoverPrice": 69.99,
      "currency": "USD",
      "category": "AI & Consciousness",
      "coverImage": "https://images.unsplash.com/photo-1620712943543-bcc4688e7485?w=400&h=600&fit=crop",
      "format": ["ebook", "audiobook", "hardcover"],
      "pages": 412,
      "rating": 4.9,
      "badge": "AI ENHANCED",
      "gumroadId": "consciousness-revolution",
      "digitalFile": "/books/teneo/consciousness-revolution.pdf"
    },
    {
      "id": "pattern-code",
      "title": "The Pattern Code",
      "author": "Alexandra Sterling & Teneo AI",
      "description": "Decoding the hidden algorithms that govern reality",
      "longDescription": "Discover the mathematical patterns that underlie all existence. This AI-enhanced exploration reveals how reality operates on fundamental algorithms.",
      "price": 34.99,
      "originalPrice": 54.99,
      "hardcoverPrice": 74.99,
      "currency": "USD",
      "category": "Science & Reality",
      "coverImage": "https://images.unsplash.com/photo-1635070041078-e363dbe005cb?w=400&h=600&fit=crop",
      "format": ["ebook", "audiobook", "hardcover"],
      "pages": 389,
      "rating": 4.8,
      "badge": "BESTSELLER",
      "gumroadId": "pattern-code",
      "digitalFile": "/books/teneo/pattern-code.pdf"
    },
    {
      "id": "simulation-theory-decoded",
      "title": "Simulation Theory Decoded",
      "author": "Professor Zhang Wei & Teneo AI",
      "description": "AI reveals the computational nature of our universe",
      "longDescription": "REALITY-SHATTERING EVIDENCE! Teneo's AI has analyzed millions of data points to reveal compelling evidence that our universe operates on computational principles.",
      "price": 39.99,
      "originalPrice": 59.99,
      "hardcoverPrice": 79.99,
      "currency": "USD",
      "category": "Future Paradigms",
      "coverImage": "https://images.unsplash.com/photo-1559494007-9f5847c49d94?w=400&h=600&fit=crop",
      "format": ["ebook", "audiobook", "hardcover"],
      "pages": 445,
      "rating": 4.7,
      "badge": "CONTROVERSIAL",
      "gumroadId": "simulation-decoded",
      "digitalFile": "/books/teneo/simulation-decoded.pdf"
    },
    {
      "id": "collective-unconscious-mapped",
      "title": "The Collective Unconscious: Mapped by AI",
      "author": "Dr. Elena Vasquez & Teneo AI",
      "description": "First complete map of humanity's shared psyche",
      "longDescription": "UNPRECEDENTED BREAKTHROUGH! Using advanced neural networks, Teneo AI has created the first comprehensive map of Jung's collective unconscious.",
      "price": 44.99,
      "originalPrice": 64.99,
      "hardcoverPrice": 84.99,
      "currency": "USD",
      "category": "AI & Consciousness",
      "coverImage": "https://images.unsplash.com/photo-1557804506-669a67965ba0?w=400&h=600&fit=crop",
      "format": ["ebook", "audiobook", "hardcover"],
      "pages": 523,
      "rating": 4.9,
      "badge": "ACADEMIC",
      "gumroadId": "collective-mapped",
      "digitalFile": "/books/teneo/collective-mapped.pdf"
    },
    {
      "id": "quantum-success-formula",
      "title": "The Quantum Success Formula",
      "author": "Michael Chen & Teneo AI",
      "description": "AI discovers the quantum mechanics of achievement",
      "longDescription": "SUCCESS REDEFINED! Teneo's quantum AI has uncovered the hidden quantum principles that govern success and achievement.",
      "price": 32.99,
      "originalPrice": 52.99,
      "hardcoverPrice": 72.99,
      "currency": "USD",
      "category": "Hidden Patterns",
      "coverImage": "https://images.unsplash.com/photo-1451187580459-43490279c0fa?w=400&h=600&fit=crop",
      "format": ["ebook", "audiobook", "hardcover"],
      "pages": 356,
      "rating": 4.8,
      "badge": "PRACTICAL",
      "gumroadId": "quantum-success",
      "digitalFile": "/books/teneo/quantum-success.pdf"
    },
    {
      "id": "future-human-ai-merge",
      "title": "The Future Human: AI-Enhanced Evolution",
      "author": "Dr. Kenji Nakamura & Teneo AI",
      "description": "The inevitable merger of human and artificial intelligence",
      "longDescription": "THE NEXT EVOLUTION! This visionary work reveals the inevitable path of human-AI integration and the transformations that will redefine humanity.",
      "price": 49.99,
      "originalPrice": 69.99,
      "hardcoverPrice": 89.99,
      "currency": "USD",
      "category": "Future Paradigms",
      "coverImage": "https://images.unsplash.com/photo-1607799279861-4dd421887fb3?w=400&h=600&fit=crop",
      "format": ["ebook", "audiobook", "hardcover"],
      "pages": 478,
      "rating": 4.9,
      "badge": "FUTURE",
      "gumroadId": "future-human",
      "digitalFile": "/books/teneo/future-human.pdf"
    }
  ],
  "collections": [
    {
      "id": "truth-seeker-collection",
      "name": "Truth Seeker Collection",
      "title": "Complete Revolutionary Library",
      "description": "Every paradigm-shifting book created with Teneo AI",
      "books": ["consciousness-revolution", "pattern-code", "simulation-theory-decoded", "collective-unconscious-mapped", "quantum-success-formula", "future-human-ai-merge"],
      "price": 149.99,
      "originalPrice": 374.94,
      "savings": 60,
      "badge": "Save 60%",
      "bonus": "EXCLUSIVE: AI Book Generation Masterclass + 1-on-1 AI Consultation",
      "gumroadId": "truth-seeker-collection"
    },
    {
      "id": "consciousness-trilogy",
      "name": "Consciousness Trilogy",
      "title": "The Complete Consciousness Collection",
      "description": "Master the AI revelations about human awareness",
      "books": ["consciousness-revolution", "collective-unconscious-mapped", "future-human-ai-merge"],
      "price": 89.99,
      "originalPrice": 164.97,
      "savings": 45,
      "badge": "Essential Reading",
      "bonus": "BONUS: Consciousness Enhancement Audio Program",
      "gumroadId": "consciousness-trilogy"
    }
  ]
}